prime_nos/__init__.py
prime_nos/core.py
prime_nos-0.2.5.dist-info/licenses/LICENSE
prime_nos-0.2.5.dist-info/METADATA
prime_nos-0.2.5.dist-info/WHEEL
prime_nos-0.2.5.dist-info/top_level.txt
prime_nos-0.2.5.dist-info/RECORD
