Metadata-Version: 2.4
Name: prime_nos
Version: 0.2.5
Summary: A simple library to check for prime and coprime numbers
Author: Venkatesh
License: MIT
Requires-Python: >=3.6
License-File: LICENSE
Dynamic: author
Dynamic: description
Dynamic: description-content-type
Dynamic: license
Dynamic: license-file
Dynamic: requires-python
Dynamic: summary
